zenroom.cpython-38-arm-linux-gnueabihf.so
zenroom/__init__.py
zenroom/_config.py
zenroom/zenroom.py
zenroom-3.17.1.dist-info/METADATA
zenroom-3.17.1.dist-info/WHEEL
zenroom-3.17.1.dist-info/top_level.txt
zenroom-3.17.1.dist-info/RECORD
