Metadata-Version: 2.1
Name: zenroom
Version: 3.17.1
Summary: Zenroom for Python: Bindings of Zenroom library for Python.
Home-page: https://github.com/dyne/Zenroom
Author: Danilo Spinella, David Dashyan, Puria Nafisi Azizi
Author-email: danyspin@dyne.org, mail@davie.li, puria@dyne.org
License: AGPLv3
Project-URL: Homepage, https://zenroom.org
Project-URL: Source Code, https://github.com/dyne/Zenroom
Project-URL: Documentation, https://dev.zenroom.org/
Keywords: zenroom,crypto-language-processing,virtual-machine,blockchain,crypto,ecc,dyne,ecdh,ecdsa,zero-knowledge-proofs,javascript,npm,ecp2,miller-loop,hamming-distance,elgamal,aes-gcm,aead,seccomp,goldilocks
Platform: UNKNOWN
Classifier: Development Status :: 3 - Alpha
Classifier: Intended Audience :: Developers
Classifier: License :: OSI Approved :: GNU Affero General Public License v3
Classifier: Operating System :: POSIX :: Linux
Classifier: Operating System :: MacOS :: MacOS X
Classifier: Programming Language :: Python :: 3
Classifier: Programming Language :: Python :: 3.8
Classifier: Programming Language :: Python :: 3.9
Classifier: Programming Language :: Python :: 3.10
Classifier: Programming Language :: Python :: 3.11
Classifier: Programming Language :: Python :: 3 :: Only
Classifier: Topic :: Security
Requires-Python: >=3.8, <4
Provides-Extra: dev
Provides-Extra: test
Requires-Dist: pytest ; extra == 'test'
Requires-Dist: schema ; extra == 'test'
